{"songs": [{"title": "Starring Role", "album": "Electra Heart", "year": "2012-04-27", "lyrics": "[Verse 1]\nYou're hard to hug, tough to talk to\nAnd I never fall asleep when you're in my bed\nAll you give me is a heartbeat\nI've turned into a statue\nAnd it makes me feel depressed\n'Cause the only time you open up is when we get undressed\n\n[Pre-Chorus 1]\nYou don't love me, big fucking deal\nI'll never tell you how I feel\nYou don't love me, not a big deal\nI'll never tell you how I feel\n\n[Chorus]\nIt almost feels like a joke to play out a part\nWhen you are not the starring role in someone else's heart\nYou know I'd rather walk alone than play a supporting role\nIf I can't get the starring role\n\n[Verse 2]\nSometimes I ignore you, so I feel in control\n'Cause really, I adore you and I can't leave you alone\nFed up with the fantasies that cover what is wrong\nCome on, baby, let's just get drunk, forget we don't get on\n\n[Pre-Chorus 2]\nYou're like my dad, you'd get on well\nI send my best regards from Hell\n\n[Chorus]\nIt almost feels like a joke to play out a part\nWhen you are not the starring role in someone else's heart\nYou know I'd rather walk alone than play a supporting role\nIf I can't get the starring role\n\n[Bridge]\nI never sang for love, I never had a heart to mend\nBecause before the start began, I always saw the end\nYeah, I wait for you to open up, to give yourself to me\nBut nothing's ever gonna give, I'll never set you free\nYeah I'll never set you free\n\n[Chorus]\nIt almost feels like a joke to play out a part\nWhen you are not the starring role in someone else's heart\nYou know I'd rather walk alone than play a supporting role\nIf I can't get the starring role\n\n[Outro]\nThe starring role", "image": "https://images.genius.com/6f46ff21e40435539c031c6ff9c6f253.1000x1000x1.jpg"}], "artist": "MARINA"}