{"songs": [{"title": "True (Acoustic)", "album": "LOVE + FEAR (Acoustic) - EP", "year": "2019-09-13", "lyrics": "[Verse 1]\nEverybody tells us what to do\nThink they always know what's good for you\nWe know they\u2005don't\u2005really have a\u2005clue\nOoh-ooh-ooh\nPeople like to tell you what\u2005to think, think, think\nSometimes it feels right to do the wrong, wrong thing\nLet it go and listen to your own instincts\nOoh-ooh-ooh\n\n[Pre-Chorus]\n'Cause you don't need nobody else\nWhen you are true, true to yourself\nYou're skin and bone, you're full of fear\nBut you are just a human being\n\n[Chorus]\nAlways said we're gonna be true\nWe will never change, we will never change\nThey could never do it better\nThan when we are, are together\nAlways said we're gonna be true\nWe will never change, we will never change\nThey could never do it better\nThan when we are, are together\n\n[Verse 2]\nDon't need to add nothing on your skin\nBe happy with the body that you're in\nBeing who you are don't cost a thing\nOoh-ooh-ooh\n\n[Pre-Chorus]\n'Cause you don't need nobody else\nWhen you are true, true to yourself\nYou're skin and bone, you're full of fear\nBut you are just a human being\n\n[Chorus]\nAlways said we're gonna be true\nWe will never change, we will never change\nThey could never do it better\nThan when we are, are together\n\n[Bridge]\nAh, ah-ah-ah-ah-ah, ah-ah\nAh, ah-ah-ah-ah-ah, ah-ah\n\n[Chorus]\nAlways said we're gonna be true\nWe will never change, we will never change\nThey could never do it better\nThan when we are, are together\nAlways said we're gonna be true\nWe will never change, we will never change\nThey could never do it better\nThan when we are, are together\n\n[Outro]\nAh, ah-ah-ah-ah-ah, ah-ah\nAh-ah, ah-ah-ah-ah-ah, ah-ah", "image": "https://images.genius.com/0bcbe347a05dd295a86de30052ad6653.1000x1000x1.jpg"}], "artist": "MARINA"}