{"songs": [{"title": "Emotional Machine", "album": "LOVE + FEAR", "year": "2019-04-26", "lyrics": "[Verse 1]\nIt's hard to see\nThat you wanna be free\n'Cause I don't love you\nIn the way that you want me to\n\n[Pre-Chorus]\nCut from devotion, lost in an ocean\nOut of emotion for you\n\n[Chorus]\nI'm a machine\nAn emotional being\nSince I was a teen\nCut my feelings off clean, clean\n\n[Verse 2]\nIt's no excuse\nTo treat me like you do\nMy perception is skewed\n'Cause I know what you went through\n\n[Pre-Chorus]\nCut from devotion, lost in an ocean\nOut of emotion for you\n\n[Chorus]\nI'm a machine\nAn emotional being\nSince I was a teen\nCut my feelings off clean, clean\n\n[Post-Chorus]\nOoh, ooh\nOoh, ooh\n\n[Bridge]\nDid you ever truly love me?\n(Did you ever truly love me?)\nWere you just too scared to be free?\n(Are you just too scared to be free?)\nMy God is dying silently (My God is dying silently)\nNobody believes, nobody believes\n\n[Chorus]\nI'm a machine (Oh)\nAn emotional being (Oh)\nSince I was a teen (Oh)\nCut my feelings off clean, clean\nI'm a machine\n(Should I pretend that you didn't exist?)\nAn emotional being\n(Should I act like you're somebody I miss?)\nSince I was a teen\n(A velvet glove around an iron fist)\nCut my feelings off clean, clean\n(If you wanna survive, then ignorance is bliss)\n\n[Post-Chorus]\nOoh, ooh\nOoh, ooh", "image": "https://images.genius.com/2461040e62c5830adb6b13e9034f8068.1000x1000x1.png"}], "artist": "MARINA"}