{"songs": [{"title": "Only Want You (Live on BBC Radio 2)", "album": null, "year": "2019-04-27", "lyrics": "[Intro]\nNo, no, no\n\n[Verse 1]\nI don't want another night of tryna find\nAnother you, another rock bottom\nI don't wanna wear another mini dress\nTo impress a potential problem\nI don't wanna spend the night at someone's place\nTo fill the space that you used to walk in\nI don't want another number in my phone\nSomeone to hold at three in the morning\n\n[Chorus]\nI don't want somebody like you\nI only want you, I only want you, yeah\nI don't want somebody brand new\nI only want you, I only want you, yeah\nGuess I had to leave, had to leave, had to leave ya\nJust to need, just to need ya\nI don't want somebody like you\nI only want you, I only want you, yeah\n\n[Verse 2]\nI know I'm the one who ruined everything\nAnd made you think that it was all your fault\nAnd I know that sorry's only just a word\nAnd when it hurts, it isn't that simple\nBut I know that if you look me in the eyes\nYou can't deny that we're something different\nAnd I know I'm going looking for your kiss\nOn someone's lips to know that I miss ya\n\n[Chorus]\nI don't want somebody like you\nI only want you, I only want you, yeah\nI don't want somebody brand new\nI only want you, I only want you, yeah\nGuess I had to leave, had to leave, had to leave ya\nJust to need, just to need ya\nI don't want somebody like you\nI only want you, I only want you, yeah\n\n[Bridge]\nI don't want another night of tryna find\nAnother you, another rock bottom\nI don't wanna wear another mini dress\nTo impress a potential problem\n\n[Chorus]\nI don't want somebody like you\nI only want you, I only want you, yeah\nI don't want somebody brand new\nI only want you, I only want you, yeah\nGuess I had to leave, had to leave, had to leave ya\nJust to need, just to need ya\nI don't want somebody like you\nI only want you, I only want you, yeah", "image": "https://images.genius.com/0488f4b6a6eaa454411e14a31e3ee80f.1000x1000x1.jpg"}], "artist": "MARINA"}