{"songs": [{"title": "Valley of the Dolls", "album": "Electra Heart", "year": "2012-04-27", "lyrics": "[Verse 1]\nIn the valley of the dolls, we sleep\nWe sleep\nGot a hole inside of me\nOf me\n\n[Pre-Chorus]\nBorn with a void\nHard to destroy with love or hope\nBuilt with a heart, broken from the start\nAnd now I die slow\n\n[Chorus]\nIn the valley of the dolls, we sleep\nGot a hole inside of me\nLiving with identities\nThat do not belong to me\nIn my life, I got this far\nNow I\u2019m ready for the last hoorah\nDying like a shooting star\nIn the valley\nIn the valley\nIn the valley\n\n[Verse 2]\nPick a personality for free\nWhen you feel like nobody\nBody\n\n[Pre-Chorus]\nBorn with a void\nHard to destroy with love or hope\nBuilt with a heart, broken from the start\nAnd now I die slow\n\n[Chorus]\nIn the valley of the dolls, we sleep\nGot a hole inside of me\nLiving with identities\nThat do not belong to me\nIn my life, I got this far\nNow I\u2019m ready for the last hoorah\nDying like a shooting star\nIn the valley\nIn the valley\nIn the valley\n\n[Bridge]\nBack to zero, here we go again, again\nRacing down into oblivion\nBack to zero, here we go\nI can feel it coming to the end, the end\n\n[Chorus]\nIn the valley of the dolls, we sleep\nGot a hole inside of me\nLiving with identities\nThat do not belong to me\nIn my life, I got this far\nNow I\u2019m ready for the last hoorah\nDying like a shooting star\nIn the valley\nIn the valley\nIn the valley\n\n[Outro]\nIn the valley\nIn the valley", "image": "https://images.genius.com/6f46ff21e40435539c031c6ff9c6f253.1000x1000x1.jpg"}], "artist": "MARINA"}