{"songs": [{"title": "The West Coast of Clare", "album": "Want Some?", "year": null, "lyrics": "Sorrow and sadness, bitterness, grief\nMemories I have of you\nWon't leave me in peace\nMy mind was running back\nTo the west coast of Clare\nThinking of you\nAnd the times we had there\n\nI walked to Spanish Point\nI knew I'd find you there\nI stood on the white strand\nYou were everywhere\nVivid memories fade\nBut the mood still remains\nI wish I could go back\nAnd be with you again\n\nIn Milltown there's a pub\nIt\u2019s there that I sat down\nI see you everywhere\nYour face is all around\nThe search for times past\nContains such sweet pain\nI'll banish lonesome thoughts\nBut they\u2019ll return again\n\nI walk along the shore\nThe rain in my face\nMy mind is numb with grief\nOf you there is no trace\nI'll think of this again\nIn far off lands I roam\nWalking with you\nBy this cold Atlantic fog\n\nSorrow and sadness, bitterness, grief\nMemories I have of you\nWon't leave me in peace\nMy mind was running back\nTo the west coast of Clare\nThinking of you\nAnd the times we had there", "image": "https://images.genius.com/0b0266eaaf811902ed364cdd0bd8cb41.600x600x1.png"}], "artist": "Ed Sheeran"}