{"songs": [{"title": "Falling", "album": "8 Letters", "year": "2018-08-31", "lyrics": "[Verse 1: Corbyn Besson]\nGirls like you, they just don't understand\nDidn't mean harm but you killed a man\nLoving you never was in the plan\nStuck in your waves, I sink in your sand\n\n[Pre-Chorus: Jonah Marais]\nSwear I saw it comin'\nI'm a fool for wantin\u2019\nYou don't wanna be rushed\nYou don't wanna be touched\nIt's a shame girls like you don't know how to love\nTried to give you my all, but it's not enough\n\n[Chorus: Jack Avery]\nCan't you see that I'm falling?\nCan't you see that I'm falling, falling for you?\nShow me where your heart is\nCan't you see that I'm falling, falling for you?\nCan't you see that I'm honest, and I want this?\nCan't believe that I'm falling, like this for you\nCan't you see that I'm falling?\nI'm falling, falling for you\n\n[Post-Chorus: All]\nOoh, ooh, ooh (falling, falling)\nOoh, ooh, ooh (falling, falling)\n\n[Verse 2: Zach Herron]\nAnd it's crazy the things I would do for us\nBut the stars don't align, they're not here for us\nIt's a shame girls like you don't know how to trust\nWish my feelings would turn 'round from love to lust\n\n[Pre-Chorus: Jonah Marais]\nSwear I saw it comin'\nI'm a fool for wantin\u2019\nYou don't wanna be rushed\nYou don't wanna be touched\nIt's a shame girls like you don't know how to love\nTried to give you my all but it's not enough\n\n[Chorus: Jack Avery]\nCan't you see that I'm falling?\nCan't you see that I'm falling, falling for you?\nShow me where your heart is\nCan't you see that I'm falling, falling for you?\nCan't you see that I'm honest, and I want this?\nCan't believe that I'm falling, like this, for you\nCan't you see that I'm falling?\nI'm falling, falling for you\n\n[Interlude: Daniel Seavey]\nIn my dreams, in my hopes\nIn my mind, they remind me of you\nShould've left when I could, can't get out\nI don't know what to do\n\n[Bridge: Daniel Seavey]\nYou can dig my grave, 'cause I can't be saved\nLike a grain of sand lost in a tidal wave\nIn a broken place, no I can't be traced\nWish you handled my feelings in better ways\n\n[Chorus: Jack Avery]\nCan't you see that I'm falling? (falling for, falling for)\nCan't you see that I'm falling, falling for you?\nShow me where your heart is (oh, oh)\nCan't you see that I'm falling, falling for you?(ooh)\nCan't you see that I'm honest, and I want this?\nCan't believe that I'm falling, like this for you\nCan't you see that I'm falling?\nI'm falling, falling for you\n\n[Post-Chorus: Jack Avery, All]\nFalling for you\nOoh, ooh, ooh (falling, falling)\nI'm falling for you\nOoh, ooh, ooh (falling, falling)", "image": "https://images.genius.com/b111db0d05362afd7928648a08e05887.1000x1000x1.jpg"}], "artist": "Why Don\u2019t We"}