{"songs": [{"title": "Not In That Way", "album": "In the Lonely Hour", "year": "2014-05-26", "lyrics": "[Verse 1]\nAnd I hate to say I love you\nWhen it's so hard for me\nAnd I hate to say I want you\nWhen you make it so clear\nYou don't want me\n\n[Chorus]\nI'd never ask you cause deep down\nI'm certain I know what you'd say\nYou'd say I'm sorry, believe me, I love you\nBut not in that way\n\n[Verse 2]\nAnd I hate to say I need you\nI'm so reliant, I'm so dependent, I'm such a fool\nWhen you're not there, I find myself singing the blues\nCan't bear, can't face the truth\n\n[Link]\nYou will never know that feeling\nYou will never see through these eyes\n\n[Chorus]\nI'd never ask you cause deep down\nI'm certain I know what you'd say\nYou'd say I'm sorry, believe me, I love you\nBut not in that way\n\n[Outro]\nYou'd say I'm sorry, believe me, I love you\nBut not in that way", "image": "https://images.genius.com/044cdf9dc1238afafafeea6325d851f4.1000x1000x1.jpg"}], "artist": "Sam Smith"}