{"songs": [{"title": "I Rise (Tracy Young\u2019s Pride Intro Radio Remix)", "album": "I Rise (Tracy Young Remixes) - EP", "year": "2019-07-19", "lyrics": "[Intro: Emma Gonzalez]\nB.S\n\n[Pre-Chorus: Madonna & Emma Gonzalez]\nI'm goin' through it, yeah\nI know you see the tragic in it\nJust hold on to the little bit of magic in it\nI can't break down now\nI can't take that now\nDied a thousand times\nManaged to survive\nI can't break down now\nI can't take that (I can't take that) (B.S.)\n\n[Chorus: Madonna]\nI rise, I rise\nI rise up above it all\n\n[Verse: Madonna]\nThere's nothin' you can do to me that hasn't been done\nNot bulletproof, shouldn't have to run from a gun\nRiver of tears ran dry, let 'em run\nNo game that you can play with me, I ain't won\n\n[Pre-Chorus: Madonna & Emma Gonzalez]\n'Cause I'm goin' through it, yeah\nI know you see the tragic in it\nJust hold on to the little bit of magic in it\nI can't break down now\nI can't take that now (I can't take that now)\nDied a thousand times\nManaged to survive (I managed to survive)\nI can't break down now\nI can't take that (I can't take that) (B.S.)\n\n[Chorus: Madonna]\n(I rise) I rise, I rise\n(Rise) I rise up above it, up above it\n(I rise) I rise, I rise\n(Rise) I rise up above it all\nI managed to survive\n\n[Bridge: Emma Gonzalez]\nUs kids don't know what we're talking about\nThat we're too young to understand how the government works\nWe call B.S\n\n[Bridge 2: Madonna & Emma Gonzalez]\nFreedom's what you choose to do with what's been done to you\nNo one can hurt you now unless you want them to\nNo one can hurt you now unless you love 'em too (B.S.)\nUnless you love 'em too\n\n[Pre-Chorus: Madonna]\n'Cause I'm going through it\nYeah, I know you see the tragic in it\nJust hold on to the little bit of magic in it (Magic in it)\nI can't break down now\nI can't take that (I can't take that)\n\n[Chorus: Madonna]\n(I rise) I rise, I rise\n(Rise) I rise up above it, up above it\n(I rise) I rise, I rise\n(Rise) I rise up above it all\n\n[Outro: Madonna]\nYeah, we gonna rise up\nYeah, we gonna rise up\nYeah, we gonna get up\nYeah, we gonna get up\nYeah, we gonna get up\nYes, we can, we can get it together\nWe'll rise up, we can get it together", "image": "https://images.genius.com/b84c60b350f5dc2d0b337924e14f2b23.600x600x1.jpg"}], "artist": "Madonna"}