{"songs": [{"title": "All I Want For Christmas", "album": "Holiday Bundle - EP", "year": "2010-11-30", "lyrics": "[Verse 1]\nI don\u2019t want a lot for Christmas\nThere is just one thing I need\nI don\u2019t care about the presents underneath the Christmas tree\n\n[Chorus 1]\nI just want you for my own more than you could ever know\nMake my wish come true\nAll I want for Christmas is you\nIt\u2019s YOU\n\n[Verse 2]\nI don\u2019t want a lot for Christmas\nThere is just one thing I need\nDon\u2019t care about the presents underneath the Christmas tree\nI don\u2019t need to hang my stocking there upon the fireplace\nSanta Claus won\u2019t make me happy with a toy on Christmas day\n\n[Chorus 1]\n\n[Verse 3]\nI won\u2019t ask for much this Christmas\nI won\u2019t even wish for snow\nI\u2019m just gonna keep on waiting underneath the mistletoe\nI won\u2019t make a list and sent it to the North Pole for Saint Nick\nI won\u2019t even stay awake to hear those magic reindeer\u2019s click\n\n[Verse 4]\nCause I just want you here tonight\nHolding onto me so tight\nWhat more can I do?\n\nAll I want for Christmas is you\nYou baby\n\n[Verse 5]\nOh! All the lights are shining so brightly everywhere (so brightly baby)\nAnd the sound of children\u2019s laughter fills the air\nAnd everyone is singing\nI hear those sleigh bells ringing\nSanta won\u2019t you bring me the one I really need\nWon\u2019t you please bring my baby to me? oh\n\n[Verse 6]\nI don\u2019t want a lot for Christmas\nThis is all I\u2019m asking for\nI just wanna see my baby standing right outside my door\nI just want you for my own more than you could ever know\nMake my wish come true\nBaby all I want for Christmas is you\nYou baby\n\n[Chorus 2]\nAll I want for Christmas is you baby\nYou\u2019re all I want\nYou\u2019re all I need\nChristmas day baby you and me\n\n[Chorus 2]", "image": "https://images.genius.com/ca489ea4456c06cf170e5e94856561cc.1000x1000x1.jpg"}], "artist": "Big Time Rush"}