{"songs": [{"title": "Revolution", "album": "Big Time Movie Soundtrack", "year": null, "lyrics": "Yeah!\n\n[Verse 1: Kendall]\nYou say you want a revolution\nWell, you know\nWe all want to change the world\n\n[Verse 2: Carlos]\nYou tell me that it's evolution\nWell, you know\nWe all want to change the world\n\n[Verse 3: James]\nBut when you talk about destruction\nDon't you know that you can count me out\n\n[Chorus: Main]\nDon't you know it's gonna be all right\nAll right, all right\n\n[Verse 5: James]\nYou say you got a real solution\nWell, you know\nWe'd all love to see the plan\n\n[Verse 6: Logan]\nYou ask me for a contribution\nWell, you know\nWe're doing what we can\n\n[Verse 7: Kendall]\nBut when you want money\nFor people with minds that hate\nAll I can tell is brother you have to wait\n\n[Chorus :Main]\n\nAh\nAh, ah, ah, ah, ah\n\n[Verse 8: James]\nYou say you'll change the constitution\nWell, you know\nWe all want to change your head\n\n[Verse 9: Logan]\nYou tell me it's the institution\nWell, you know\nYou better free you mind instead\n\n[Verse 10: Logan]\nBut if you go carrying pictures of chairman mao\nYou ain't going to make it with anyone any how\nDon't you know it's gonna be all right\nAll right, all right\nAll right, all right, all right\nAll right, all right, all right", "image": "https://images.genius.com/3c10d44f72f20328d570ca0c09253bfb.1000x1000x1.jpg"}], "artist": "Big Time Rush"}