{"songs": [{"title": "Say It", "album": "Good Girl Gone Bad", "year": "2007-05-31", "lyrics": "[Intro]\nYou should tell me what's bugging you\nAnd I'ma tell ya 'bout me\nMake a wish and tell me your deepest thoughts\nAnd I'ma make it easy\nMake a wish and tell me what's bugging you\nAnd I'ma tell ya 'bout me\nMake a wish and tell me your deepest thoughts\nAnd I'ma make it easy\n\n[Verse 1]\nEmotions running wild\nI could feel it when I'm next to you\nSomething's on ya mind\nYou wanna stay, but won't tell me\nIt's about ya secrecy\nSo what are you tryna hide?\nI know what the look means\nYou hold my hand so tightly\nWhenever we say goodbye\nStanding by the door\nI could tell you can't take no more\nBlow your secret open wide\n\n[Chorus]\nSo maybe if you say it (Say it)\nTell me what it is you like (Like)\nBaby, baby, don't be shy (Shy)\nMaybe you can spend the night (Night)\nIf you say it\nBut if you playing (Not with it)\n'Cause you know what I wanna hear (Hear)\nSay it, that'll make it more clear (Clear)\nI need to know how you feel\nSo baby, why won't you (Say it)\nSay it (Say it)\n\n[Post-Chorus]\nWon't, won't you tell me\nWhat, what's goin' on?\nWhy, why you waitin' on it?\nWhat you waiting for?\nSoon you should tell me or I might be gone\nBut I'm here for you, baby\nYou should put me on\n\n[Verse 2]\nI won't shoot you down\nMake you feel some kinda way\nIf you'll be honest with me\nPut away your pride\nI can see it in your face\nYou want me permanently (Uh)\nLike how I whine when we dancing\nI know how it happened\nAnd I'm right there with you\nBut I won't be the first to put myself out there\nThe feeling is mutual\nBut I bet if you (Say it)\n\n[Chorus]\nSo maybe if you say it (Say it)\nTell me what it is you like (Like)\nBaby, baby, don't be shy (Shy)\nMaybe you can spend the night (Night)\nIf you say it\nBut if you playing (Not with it)\n'Cause you know what I wanna hear (Hear)\nSay it, that'll make it more clear (Clear)\nI need to know how you feel\nSo baby, why won't you (Say it)\nSay it (Say it)\n\n[Bridge]\nYour eyes steady talking\nAnd you're tryna fight it\nBut some things, baby, are not worth hiding\nAnd we can find heaven\nIf we go look together\nSo won't, won't you tell me\nAnd get it off your chest\nYour eyes steady talking\nAnd you're tryna fight it\nBut some things, baby, are not worth hiding\nAnd we can find heaven\nIf we go look together\nSo won't, won't you tell me\nAnd get it off your chest\n\n[Chorus]\nSo maybe if you say it (Say it)\nTell me what it is you like (Like)\nBaby, baby, don't be shy (Shy)\nMaybe you can spend the night (Night)\nIf you say it\nBut if you playing (Not with it)\n'Cause you know what I wanna hear (Hear)\nSay it, that'll make it more clear (Clear)\nI need to know how you feel\nSo baby why won't you (Say it)\nSay it (Say it)\n\n[Bridge]\nYour eyes steady talking\nAnd you're tryna fight it\nBut some things, baby, are not worth hiding\nAnd we can find heaven\nIf we go look together\nSo won't, won't you tell me\nAnd get it off your chest\nYour eyes steady talking\nAnd you're tryna fight it\nBut some things, baby, are not worth hiding\nAnd we can find heaven\nIf we go look together\nSo won't, won't you tell me\nAnd get it off your chest\n\n[Chorus]\nSo maybe if you say it (Say it)\nTell me what it is you like (Like)\nBaby, baby, don't be shy (Shy)\nMaybe you can spend the night (Night)\nIf you say it\nBut if you playing (Not with it)\n'Cause you know what I wanna hear (Hear)\nSay it, that'll make it more clear (Clear)\nI need to know how you feel\nSo baby, why won't you (Say it)\nSay it (Say it)", "image": "https://images.genius.com/dabed3ab4ac63f01b11ce21e95e5c5db.1000x989x1.jpg"}], "artist": "Rihanna"}