{"songs": [{"title": "Begging (Demo)", "album": null, "year": null, "lyrics": "[Verse 1]\nAll of these highs\nAnd all of these lows\nDon't keep me company\nI've been breathing you in\nAnd drinking you down\nYou're the only remedy\n\n[Pre-Chorus]\nSay you're gonna hold my head up\nSay you're gonna break my fall\nSay you're gonna stay forever\nBaby, this is all I want\n\n[Chorus]\n'Cause all my bones are begging me to beg for you\nBegging me to beg for your love\nOh, my lungs are begging me to beg for you\nBegging me to beg for your love\nSwear I'm gonna hold your head up\nSwear I'm gonna break your fall\nSwear we're gonna last forever\nBaby, this is all I want\n'Cause all my bones are begging me to beg for you\nBegging me to beg for your love\n\n[Verse 2]\nLosing my mind\nDreaming I'll find\nAnother kind of love\nBut this blood in my veins\nAnd the thought of your taste\nNo, I can't give it up\nSo look at my face\nI'm not running away\n\n[Chorus]\n'Cause all my bones are begging me to beg for you\nBegging me to beg for your love\nSwear I'm gonna hold your head up\nSwear I'm gonna break your fall\nSwear we're gonna last forever\nBaby, this is all I want\n'Cause all my bones are begging me to beg for you\nBegging me to beg for your love\n\n[Instrumental Break]\n\n[Breakdown]\nSay you're gonna hold my head up\nSay you're gonna break my fall\nSay you're gonna stay forever\nBaby, this is all I want\nSwear I'm gonna hold your head up\nSwear I'm gonna break your fall\nSwear we're gonna last forever\nBaby, this is all I want\n\n[Chorus]\n'Cause all my bones are begging me to beg for you\nBegging me to beg for your love\nOh, my lungs are begging me to beg for you\nBegging me to beg for your love", "image": "https://images.genius.com/307cb0e7a24adbee7c04394d11091102.1000x1000x1.jpg"}], "artist": "Dua Lipa"}