{"songs": [{"title": "Kill Your Mama", "album": "HERE", "year": "2016-11-04", "lyrics": "[Intro]\nCome on\nFeel me\nYes\n\n[Verse 1]\nShame on us, on your sons and your daughters\nThieve all your gold and we poison all your waters\nEvery piece of our soul is for sale\nNow they bought us\nThink we know it all\nThen look where it got us\n\n[Refrain 1]\nOh, mama, mama\nOh, mama, mama\nWe're crying to the wind\n\n[Verse 2]\nTryina play God\nWe been fucking with genetics\nAll that you have given and we only disrespect it\nThe rate that we\u2019re going premature Armageddon\nThat's what gonna happen if we let it\n\n[Refrain 1]\nOh, mama, mama\nOh, mama, mama\nWe're crying to the wind, mm\n\n[Chorus]\nIs there any savin' us\nWe've become so dangerous\nIs there any change in us\nEven for the sake of love\nHow you gonna kill your mama\nWhen only mama is gonna love you to the grave\n\n[Verse 3]\nKilling ourselves\nFalling down with the sickness\nMoney is the king\nIt's a dirty bloody business\nThere will be no trial\nBut the child will always witness\nIf we are in love with hell\nWhy the hell would heaven visit\n\n[Refrain 1]\nOh, mama, mama\nOh, mama, mama\nWe're crying to the wind\n\n[Verse 4]\nWhen mama gets the belt you gon' wish we didn't do it\nHad your chance for redemption\nBut you fuckin' blew it\nNow the weather is changin' it and the hurricane is movin'\nRight in your direction\nWhat direction are you choosin'\n\n[Refrain 2]\nOh, mama, mama\nOh, mama, mama\nForgive us for your pain\n\n[Chorus]\nIs there any savin' us\nWe've become so dangerous\nIs there any changing us\nEven for the sake of love\nHow you gonna kill your mama\nWhen only mama is gonna love you to the grave\n\n[Outro]\nHow you gonna kill your mama\nHow you gonna kill your mama", "image": "https://images.genius.com/4d46e56b4950d2b18a8a745d1fb4918a.1000x1000x1.jpg"}], "artist": "Alicia Keys"}