{"songs": [{"title": "I\u2019d Rather Go Blind", "album": "Cadillac Records: Music From the Motion Picture", "year": "2008-12-02", "lyrics": "[Verse 1]\nSomething told me it was over (Yeah)\nWhen I saw you and her talking deep\nSomething deep down in my soul said cry girl (cry, cry)\nWhen I saw you and that girl walking around whoo ooh\n\n[Chorus]\nI would rather, I would rather go blind boy\nThen to see you walk away from me child naw naw whoo ooh\n\n[Verse 2]\nSo you see I love you so much that I don't wanna watch you leave me baby\nMost of all I just don't\nI just don't wanna be free now whoo ooh, Woo oh\nI was just, I was just, I was just sitting here thinking of your kiss\nAnd your warm embrace yeah\nWhen a reflection in a glass that I held to my lips now baby\nRevealed these tears that are on my face whoo ooh\n\n[Chorus]\nAnd baby, and baby, baby I'd rather be blind boy\nThen to see you walk away\nWalk away from me yeah\nAnd baby, baby, baby I'd rather be blind boy\nThen to see you walk away\nWalk away from me", "image": "https://images.genius.com/bcfd51835fca3c447984a69f478ab8d3.300x300x1.jpg"}], "artist": "Beyonc\u00e9"}