{"songs": [{"title": "Destiny\u2019s Child Medley", "album": null, "year": "2009-11-23", "lyrics": "You be sayin'\nNo no no no no\nWhen it's really\nYes yes yes yes yes\n(x 4)\n\nBoy I know you want me\nI can see it in your eyes\nBut you keep on frontin'\nWhy don't you say what's on your mind\n'Cause each and everytime\nYou're near me\nYou give me signs\nBut when I ask you \"What's the deal?\"\nYou're holdin' it all inside\nIf you wanna' be with me\nYou gotta' keep it real\nTell me what's goin' on\nTell me how you feel\nBoy I know you want me\nJust as much as I want you\nSo come get my love\nAll here for you\n\nEverytime I see you with your boys\nYou pretend as if you don't want me\nWhen you get home you call me on the phone\nAnd tell me how much you care\n\nBug a boo(talk)\nYou buggin' what?\nYou buggin' Who?\nYou buggin' me\nYou make me wanna throw my pager out the window\nTell MCI to cut the phone poles\nBreak my lease so I can move\nCause you a bug-a boo, a bug-a boo\nI wanna put your number on the call block\nHave AOL make my e-mail stop\n\nCan you pay my bills\nCan you pay my telephone bills\nCan you pay my automo-bills\nIf you did then maybe we could chill\nI don't think you do\nSo, you and me are through\n\nSay my name, say my name\nIf no one is around you\nSay baby I love you\nIf you ain't runnin' game\nSay my name, say my name\nYou actin' kinda shady\nAin't callin' me baby\nWhy the sudden change?\n\nSay my name, say my name\nIf no one is around you\nSay baby I love you\nIf you ain't runnin game\nSay my name, say my name\nYou actin' kinda shady\nAin't callin' me baby\nBetter say my name!\n\nAny other day I would call\nYou would say, baby how's your day?\nBut today it ain't the same\nEvery other word is\nUh huh, yeah okay\nCould it be that you\nAre at the crib with another lady?\nIf you took it there first of all\nLet me say, I am not the one\nTo sit around and be played\nWhy do you feel you gotta lie?\nGettin' caught up in your'one game\nWhen you can not say my name\n\nI know you say that I am assuming things\nSomething's going down that's the way it seems\nShouldn't be a reason why you're acting strange\nIf nobody's holding you back from me\nCause I know how you usually do\nWhen you say everything to me times two\nWhy can't you just tell the truth?\nIf somebody's there then tell me who\n\nSay my name, say my name\nIf no one is around you\nSay baby I love you\nIf you ain't runnin' game\nSay my name, say my name\nYou actin' kinda shady\nAin't callin' me baby\nWhy the sudden change?\nSay my name, say my name\nIf no one is around you\nSay baby I love you\nIf you ain't runnin' game\nSay my name, say my name\nYou actin' kinda shady\nAin't callin' me baby\nBetter say my name!\n(all my DC's fans!)\n(yea yea yea yea, yea yea yea yea)\n\nLadies leave yo man at home(3x)\nCause it's eleven thirty and the club is jumpin', jumpin'\nBounce baby, bounce, bo-bounce bounce, bo-bounce\nTwirk it, twirk it\nShake baby, shake sha-shake shake\nWork it, work it\nTwist baby, twist tw-twist\nYou better dip that thing\n\nLucy Liu\nWith my girl, Drew\nCameron D. and Destiny\n\nQuestion: Tell me what you think about me\nI buy my own diamonds and I buy my own rings\nOnly ring your cell-y when I'm feelin lonely\nWhen it's all over please get up and leave\nQuestion: Tell me how you feel about this\nTry to control me boy you get dismissed\nPay my own fun, oh and I pay my own bills\nAlways 50/50 in relationships\n\nThe shoes on my feet\nI bought it\nThe clothes I'm wearing\nI bought it\nThe rock I'm rockin'\nI bought it\n'Cause I depend on me\nIf I want it\nThe watch I'm wearin'\nI bought it\nThe house I live in\nI bought it\nThe car I'm driving\nI bought it\nCause I depend on me\n(I depend on me)\n\nAll the women who are independent\nThrow your hands up at me\nAll the honeys who makin' money\nThrow your hands up at me\nAll the mommas who profit dollas\nThrow your hands up at me\nAll the ladies who truly feel me\nThrow your hands up at me\n\nKelly, can you handle this?\nMichelle, can you handle this?\nBeyonc\u00e9, can you handle this?\nI don't think they can handle this! (WHOO!)\n\nI don't think you ready for this jelly\nI don't think you ready for this jelly\nI don't think you ready for this\nCause my body's too bootylicious for ya babe\n\nBaby, can you handle this?\nBaby, can you handle this?\nBaby, can you handle this?\nI don't think you can handle this!\n\nNow that you're out of my life\nI'm so much better\nYou thought that I'd be weak without you\nBut I'm stronger\nYou thought that I'd be broke without you\nBut I'm richer\nYou thought that I'd be sad without you\nI laugh harder\nYou thought I wouldn't grow without you\nNow I'm wiser\nThough that I'd be helpless without you\nBut I'm smarter\nYou thought that I'd be stressed without you\nBut I'm chillin'\nYou thought I wouldn't sell without you\nSold 9 million\n\nI'm a survivor (What?)\nI'm not gon give up\nI'm gon work harder\nI'm a survivor\nI'm gonna make it\nI will survive\nKeep on survivin'\n\nI'm a survivor!!", "image": "https://images.genius.com/3e9f57e8336bc2583aa2df002893e118.300x300x1.png"}], "artist": "Beyonc\u00e9"}