{"songs": [{"title": "Amor Gitano", "album": "B\u2019Day (Deluxe Edition)", "year": "2006-09-04", "lyrics": "[Letra de \"Amor Gitano\" ft. Alejandro Fern\u00e1ndez]\n\n[Verso 1: Beyonc\u00e9 & Alejandro Fern\u00e1ndez]\nVen y qu\u00e9date conmigo\nDame el coraz\u00f3n vida m\u00eda estoy muriendo lento en mi prisi\u00f3n\nAnda dime lo que sientes quitate el pudor\nY deja de sufrir, escapa con mi amor\nY despu\u00e9s te llevare hasta donde quieras sin temor y sin fronteras hasta donde sale el sol\nContigo soy capaz de lo que sea\nNo me importa lo que venga\nPorque ya se a donde voy\n\n[Coro: Alejandro Fern\u00e1ndez & Beyonc\u00e9]\nSoy tu gitano, tu peregrino\nLa \u00fanica llave de tu destino\nEl que te cuida m\u00e1s que a su vida\nSoy tu ladr\u00f3n\nSoy tu gitana, tu compa\u00f1era\nLa que te sigue, la que te espera\nVoy a quererte aunque me saquen el coraz\u00f3n\nY aunque nos cueste la vida\nY aunque duela lo que duela\nEsta guerra la ha ganado nuestro amor\nEsta guerra la ha ganado nuestro amor\n\n[Verso 2: Beyonc\u00e9 & Alejandro Fern\u00e1ndez]\nYo nac\u00ed para tus ojos, para nadie m\u00e1s\nSiempre voy a estar en tu camino\nAlma de mi alma, coraz\u00f3n de tempestad\nDime por donde ir\nY despu\u00e9s te llevare hasta donde quiera\nSin temor y sin fronteras hasta donde sale el sol\nContigo soy capaz de lo que sea\nNo me importa lo que venga porque ya se a donde voy\n\n[Coro: Alejandro Fern\u00e1ndez & Beyonc\u00e9]\nSoy tu gitano, tu peregrino\nLa \u00fanica llave de tu destino\nEl que te cuida m\u00e1s que a su vida\nSoy tu ladr\u00f3n\nSoy tu gitana, tu compa\u00f1era\nLa que te sigue, la que te espera\nVoy a quererte aunque me saquen el coraz\u00f3n\nY aunque nos cueste la vida\nY aunque duela lo que duela\nEsta guerra la ha ganado nuestro amor\nY aunque nos cueste la vida\nY aunque duela lo que duela\nEsta guerra la ha ganado\n\n[Outro: Alejandro Fern\u00e1ndez & Beyonc\u00e9]\nNuestro amor", "image": "https://images.genius.com/92849fe8421f8f4badd36471791289f4.600x600x1.jpg"}], "artist": "Beyonc\u00e9"}