{"songs": [{"title": "I\u2019ll Be There", "album": "MTV Unplugged EP", "year": "1992-05-26", "lyrics": "[Spoken intro]\nThis next song is made popular\nBy incredible Jackson 5\nAnd it's always been one of my favorite songs\nAnd I hope it's yours\nIt's called, \"I'll be there\"\n\nOoh, ooh\n\n[Verse 1: Mariah Carey]\nYou and I must make a pact\nWe must bring salvation back\nWhere there is love\nI'll be there (I'll be there)\n\nI'll reach out my hand to you\nI'll have faith in all you do\nJust call my name\nAnd I'll be there\n\n[Chorus: Trey Lorenz]\nI'll be there to comfort you\nI'll build my world of dreams around you\nI'm so glad I found you, yeah\nI'll be there with a love so strong\nI'll be your strength\nYou know I'll keep holding on\n\n[Verse 2: Mariah Carey]\nLet me fill your heart with joy and laughter\nTogetherness, well, it's all I'm after\nJust call my name\nAnd I'll be there (I'll be there)\nYeah, yeah\n\nI'll be there to protect you (Yeah, baby)\nWith an unselfish love that respects you\nJust call my name\nAnd I'll be there (I'll be there)\n\n[Chorus: Trey Lorenz]\nI'll be there to comfort you\nBuild my world of dreams around you\nYou know I'm so glad I found you, babe (So glad, baby)\nI'll be there with a love so strong\nI'll be your strength (Be your strength)\nYou know I'll keep holding on (Holding on)\n\n[Verse 3: Mariah Carey]\nIf you should ever find someone new\nI know she'd better be good to you\nBecause if she doesn't\nThen I'll be there (I'll be there)\n\n[Outro]\nDon't you know, baby, yeah, yeah\nI'll be there\nI'll be there, yeah-yeah, yeah\nJust call my name (I'll be there)\nAnd I'll be there\nYeah, yeah, yeah, yeah-ah\n\nI'll be there, baby (I'll be there)\nYou know I'll be there, yeah-yeah-yeah-yeah, yeah-ah\nJust call my name (I'll be there)\nAnd I'll be there\n\nJust look over your shoulder\nJust call my name (Yeah)\nAnd I'll be there\n(Ooh-ooh, ooh)\n(Ooh-ooh, ooh)\n\n[Spoken]\nThank you", "image": "https://images.genius.com/3bf9c7d17d7526396f65e22bfc5a9c16.245x245x1.png"}], "artist": "Mariah Carey"}