{"songs": [{"title": "All in Your Mind", "album": "Mariah Carey ", "year": "1990-06-12", "lyrics": "[Verse 1]\nCome closer\nYou seem so far away\nThere's something I know you need to say\nI feel your emotions\nWhen I look in your eyes\n\n[Verse 2]\nYour silence\nWhispering misunderstandings\nThere's so much you need to realize\nYou'll feel my emotions\nIf you look in my eyes\n\n[Chorus]\nHey, darling\nI know you think my love is slipping away\nBut, baby, it's all in your mind (Yes)\nDon't worry\nHold on tight and hear me when I say\nBaby, it's all in your mind (Yeah. Yeah. Ooh)\n\n[Verse 3]\nBelieve me\nI believe in you\nThere's nothing this feeling couldn't do\nMove closer, my darling\nFeel the love in my eyes (Yes)\n\n[Chorus]\nHey, darling\nI know you think my love is slipping away\nBut, baby, it's all in your mind (Yes)\nDon't worry\nHold on tight and hear me when I say\nBaby, it's all in your mind (Yeah. Yes)\n\nI know you feel my love\nIn your mind, yeah\n\n[Chorus]\nHey, darling\nWell, I know you think my love is slipping away\nBut, baby, it's all in your mind (Yes, yes)\nDon't worry\nHold on tight and hear me when I say\nBaby, it's all in your mind (Yeah)\nBaby, it's all in your mind (Yes, uh, uh, hmm, hmm)\nBaby, it's all in your mind (Mind, oh, yeah, baby, ooh, darling)\nGot to let you know, baby\nBaby, it's all in your mind\nYou know my love is good now, baby, yes\nBaby, it's all in your mind\nBaby, it's all in your mind (Yeah, darling)\nBaby, it's all in your mind (Wow, ooh, ooh, ooh)\nBaby, it's all in your mind\nBaby, it's all in your mind (Oh)\nBaby, it's all in your mind", "image": "https://images.genius.com/d47fd49102911c50bbbf3bf9e57231e2.1000x1000x1.jpg"}], "artist": "Mariah Carey"}