{"songs": [{"title": "The Beautiful Ones", "album": "Butterfly", "year": "1997-09-16", "lyrics": "[Verse 1: Dru Hill With Mariah Carey]\nBaby, baby, baby\nWhat's it gonna be?\nOh, baby, baby, baby, yeah yeah\nIs it him or is it me?\nOh, don't make me waste my time\nDon't make me lose my mind baby, yeah\n\n[Verse 2: Mariah Carey]\nBaby, baby, baby\nCan't you stay with me tonight?\nOh, baby, baby, baby\nCome, on, don't my kisses please you right?\nYou were so hard to find\nThe beautiful ones, they hurt you every time\n\n[Verse 3: DeVante Swing]\nPaint a perfect picture\nAnd bring to life a vision in one's mind\n\n[Verse 4: Mariah Carey, DeVante Swing & Dru Hill]\nThe beautiful ones\n(The beautiful ones)\nAlways smash the picture\nAlways every time\n\n[Verse 5: Mariah Carey & (Dru Hill)]\nIf I told you, baby\nThat I was in love with you\nOh, baby, baby, baby\nIf we got married (Got married)\nWould that be cool?\nYou make me so confused\nThe beautiful ones\nYou always seem to lose, baby\n\n[Outro: Mariah Carey & (Dru Hill)]\nBaby, baby (Yes baby, yes, baby)\nSee the beautiful ones\n(The beautiful ones)\nSee the beautiful ones\n(The beautiful ones)\n(Do you all hear?)\n(Do you all mean?)\n'Cause I want you\nYes, I mean, I want you\nOh, yeah, baby\nI want you, oh yeah\n(I want you)\n(Alright)\nYou may not know where I'm going, baby\nI may not know, said I may not know\nSaid you may not know\nBut I mean what I mean\nBut one thing, one thing is certain, baby\nI know what I want\nAnd that's to please you, baby, to please you, baby\nThe one thing is I want you I want you\nI need you oh so bad, so bad\nI want you\n\n[Outro: Mariah Carey & Dru Hill]\nWhy, oh, why?\nWhy, oh, why?\nWhy, oh, why?\nBaby, why, oh, baby, baby, baby\nThe beautiful ones\nYou wanna love me, love me\nOr you wanna throw me away\nI gotta know\nI gotta know, baby\nGotta know, baby, baby, baby\nBaby, baby, baby\nI need you\nBaby, baby, baby\nI want you\nTell me why\nThe beautiful ones\nThey hurt you every time", "image": "https://images.genius.com/f9e30591b3620ce4e7d369afd9b008ad.1000x1000x1.jpg"}], "artist": "Mariah Carey"}