{"songs": [{"title": "Now and Then", "album": "19", "year": "2008-04-21", "lyrics": "[Verse 1]\nSometimes the hole you left hurts my heart\nSo bad it cuts through the deepest parts of me\nAnd fills up my mouth with the words that cry\nHow I still try to stay inside\n\n[Chorus]\nHearts break and hearts wait to make us grow fonder\nThen our eyes cry and souls sigh, so that we know that it hurts\nOur hearts break and hearts wait to make us grow fonder\nThen our eyes cry and souls sigh, so that we know that it hurts\n\n[Verse 2]\nEvery now and then my memories ache\nWith the empty ideas of the ones we'd have made\nBut as time goes on and my age gets older\nI love the ones I know, they're enough to picture the rest\n\n[Chorus]\n\n[Outro]\nYou know when to make me imagine you're here\nYou know when to make me imagine you're here\nYou know when to make me imagine you're here\nYou know when to make me imagine you're here", "image": "https://images.genius.com/2863f10c070e858985a13d5b5730c118.600x600x1.jpg"}], "artist": "Adele"}